trmx_agent/__init__.py
trmx_agent/cli.py
trmx_agent/config.py
trmx_agent/main.py
trmx_agent/storage.py
trmx-0.3.16.dist-info/METADATA
trmx-0.3.16.dist-info/WHEEL
trmx-0.3.16.dist-info/entry_points.txt
trmx-0.3.16.dist-info/top_level.txt
trmx-0.3.16.dist-info/RECORD
