Metadata-Version: 2.4
Name: trmx
Version: 0.3.16
Summary: A powerful terminal chat interface for multiple AI models with local session storage
Author: AirTrain Team
License: MIT
Project-URL: Homepage, https://github.com/yourusername/airtrain
Project-URL: Bug Tracker, https://github.com/yourusername/airtrain/issues
Classifier: Development Status :: 3 - Alpha
Classifier: Environment :: Console
Classifier: Intended Audience :: Developers
Classifier: License :: OSI Approved :: MIT License
Classifier: Programming Language :: Python :: 3
Classifier: Programming Language :: Python :: 3.8
Classifier: Programming Language :: Python :: 3.9
Classifier: Programming Language :: Python :: 3.10
Classifier: Programming Language :: Python :: 3.11
Classifier: Topic :: Communications :: Chat
Requires-Python: >=3.8
Requires-Dist: airtrain>=0.1.58
Requires-Dist: rich>=12.0.0
Requires-Dist: typer>=0.7.0
Requires-Dist: python-dotenv>=0.20.0
Requires-Dist: requests>=2.25.0
Requires-Dist: packaging>=21.3
Provides-Extra: dev
Requires-Dist: pytest>=7.0.0; extra == "dev"
Requires-Dist: black>=22.0.0; extra == "dev"
Requires-Dist: isort>=5.10.0; extra == "dev"
Requires-Dist: mypy>=0.950; extra == "dev"
